{
  "choices": [
    {
      "id": "10866f6e-a0a1-49d5-a703-85b1e4ef7e5a",
      "name": "add_personal_daily_task",
      "type": "Capture",
      "command": true,
      "appendLink": false,
      "captureTo": "",
      "captureToActiveFile": true,
      "createFileIfItDoesntExist": {
        "enabled": false,
        "createWithTemplate": false,
        "template": ""
      },
      "format": {
        "enabled": true,
        "format": "{{VALUE: Description}} #task #personal_task #daily_task 📅 <% moment(tp.file.title,'YYYY-MM-DD').format(\"YYYY-MM-DD\") %>"
      },
      "insertAfter": {
        "enabled": false,
        "after": "",
        "insertAtEnd": false,
        "createIfNotFound": false,
        "createIfNotFoundLocation": "top"
      },
      "prepend": true,
      "task": true,
      "openFileInNewTab": {
        "enabled": false,
        "direction": "vertical",
        "focus": true
      },
      "openFile": false,
      "openFileInMode": "default"
    },
    {
      "id": "0e5b2b66-253a-4daa-bf6c-17ddd3f440cc",
      "name": "add_work_daily_task",
      "type": "Capture",
      "command": true,
      "appendLink": false,
      "captureTo": "",
      "captureToActiveFile": true,
      "createFileIfItDoesntExist": {
        "enabled": false,
        "createWithTemplate": false,
        "template": ""
      },
      "format": {
        "enabled": true,
        "format": "{{VALUE: Description}} #task #work_task #daily_task 📅 <% moment(tp.file.title,'YYYY-MM-DD').format(\"YYYY-MM-DD\") %>"
      },
      "insertAfter": {
        "enabled": false,
        "after": "",
        "insertAtEnd": false,
        "createIfNotFound": false,
        "createIfNotFoundLocation": "top"
      },
      "prepend": true,
      "task": true,
      "openFileInNewTab": {
        "enabled": false,
        "direction": "vertical",
        "focus": true
      },
      "openFile": false,
      "openFileInMode": "default"
    }
  ],
  "macros": [
    {
      "name": "add_personal_task_to_current_daily_file_macro",
      "id": "291f430a-79e2-4723-a414-5a270a57a980",
      "commands": [
        {
          "name": "add_current_daily_file_date_to_window",
          "type": "UserScript",
          "id": "a14536e7-246b-42d5-9990-0fe6f489a7ac",
          "path": "database/scripts/add_current_daily_file_date_to_window.js",
          "settings": {}
        },
        {
          "name": "add_personal_task_to_tasks_file",
          "type": "Choice",
          "id": "aa07dc7e-613b-4d78-b300-8e813366eab7",
          "choiceId": "fd9804ed-f7f8-4c9e-b5b0-b7ada4f353a0"
        }
      ],
      "runOnStartup": false
    },
    {
      "name": "add_work_task_to_current_daily_file_macro",
      "id": "72d6a0e2-03b8-4330-b501-dc9e50b4f91b",
      "commands": [
        {
          "name": "add_current_daily_file_date_to_window",
          "type": "UserScript",
          "id": "72f6c312-41ff-4bed-9435-99c025f15de9",
          "path": "database/scripts/add_current_daily_file_date_to_window.js",
          "settings": {}
        },
        {
          "name": "add_work_task_to_tasks_file",
          "type": "Choice",
          "id": "5c26a49e-7ced-43ac-b73e-70b473eb6461",
          "choiceId": "0ff910af-f1eb-401c-8b78-5fb5cf98b1e9"
        }
      ],
      "runOnStartup": false
    }
  ],
  "inputPrompt": "single-line",
  "devMode": false,
  "templateFolderPath": "templates",
  "migrations": {
    "migrateToMacroIDFromEmbeddedMacro": true,
    "useQuickAddTemplateFolder": true,
    "incrementFileNameSettingMoveToDefaultBehavior": true,
    "mutualExclusionInsertAfterAndWriteToBottomOfFile": true
  }
}